[{"_path":"/general-info/committee-minutes","_dir":"general-info","_draft":false,"_partial":false,"_locale":"","title":"Committee Minutes","description":"","_type":"markdown","_id":"content:4.general-info:9.committee-minutes.md","_source":"content","_file":"4.general-info/9.committee-minutes.md","_stem":"4.general-info/9.committee-minutes","_extension":"md","sitemap":{"loc":"/general-info/committee-minutes"}},{"_path":"/photo-album","_dir":"","_draft":false,"_partial":false,"_locale":"","title":"Photo Album","description":"","redirect":"https://bsatroop27.smugmug.com/","_type":"markdown","_id":"content:10.photo-album.md","_source":"content","_file":"10.photo-album.md","_stem":"10.photo-album","_extension":"md","sitemap":{"loc":"/photo-album"}}]