[{"_path":"/policies-and-procedures/financial-policy","_dir":"policies-and-procedures","_draft":false,"_partial":false,"_locale":"","title":"Financial Policy","description":"","_type":"markdown","_id":"content:3.policies-and-procedures:4.financial-policy.md","_source":"content","_file":"3.policies-and-procedures/4.financial-policy.md","_extension":"md"},{"_path":"/general-info/bsa-information","_dir":"general-info","_draft":false,"_partial":false,"_locale":"","title":"Bsa Information","description":"","_type":"markdown","_id":"content:4.general-info:1.bsa-information.md","_source":"content","_file":"4.general-info/1.bsa-information.md","_extension":"md"}]